dfngen/__init__.py
dfngen/dfnclient.py
dfngen/openssl.py
dfngen/soap.py
dfnclient-0.4.9.dist-info/LICENSE
dfnclient-0.4.9.dist-info/METADATA
dfnclient-0.4.9.dist-info/WHEEL
dfnclient-0.4.9.dist-info/entry_points.txt
dfnclient-0.4.9.dist-info/top_level.txt
dfnclient-0.4.9.dist-info/RECORD
