Metadata-Version: 2.1
Name: dfnclient
Version: 0.4.9
Summary: Certificate client based on the soap API of the dfn
Home-page: https://github.com/Miterion/dfnclient
License: MIT
Platform: UNKNOWN
Requires-Dist: click (==8.0.1)
Requires-Dist: cryptography (==3.4.8)
Requires-Dist: suds-py3 (==1.4.4.1)
Requires-Dist: termcolor (==1.1.0)
